orx/__init__.py
orx-0.0.1.dist-info/LICENSE
orx-0.0.1.dist-info/WHEEL
orx-0.0.1.dist-info/METADATA
orx-0.0.1.dist-info/RECORD
